cache/__init__.py
cache/cache.py
cache.py-0.1.3.dist-info/DESCRIPTION.rst
cache.py-0.1.3.dist-info/METADATA
cache.py-0.1.3.dist-info/RECORD
cache.py-0.1.3.dist-info/WHEEL
cache.py-0.1.3.dist-info/metadata.json
cache.py-0.1.3.dist-info/top_level.txt
