Metadata-Version: 2.0
Name: cache.py
Version: 0.1.3
Summary: cacheing
Home-page: https://github.com/ohjeah/cache
Author: Markus Quade, Thomas Isele
Author-email: info@markusqua.de
License: MIT
Platform: UNKNOWN
Classifier: Programming Language :: Python
Classifier: Programming Language :: Python :: 3.5
Classifier: Programming Language :: Python :: 3.6
Requires-Dist: dill
Requires-Dist: joblib
Requires-Dist: sqlitedict
